pheval_ai_marrvel/__init__.py
pheval_ai_marrvel/cli.py
pheval_ai_marrvel/constants.py
pheval_ai_marrvel/post_process/__init__.py
pheval_ai_marrvel/post_process/post_process.py
pheval_ai_marrvel/post_process/post_process_results_format.py
pheval_ai_marrvel/prepare/__init__.py
pheval_ai_marrvel/prepare/prepare.py
pheval_ai_marrvel/prepare/prepare_input.py
pheval_ai_marrvel/run/__init__.py
pheval_ai_marrvel/run/create_apptainer_commands.py
pheval_ai_marrvel/run/create_docker_commands.py
pheval_ai_marrvel/run/prepare_next_flow_commands.py
pheval_ai_marrvel/run/run.py
pheval_ai_marrvel/runner.py
pheval_ai_marrvel/tool_specific_configuration_options.py
pheval_ai_marrvel-0.2.0.dist-info/METADATA
pheval_ai_marrvel-0.2.0.dist-info/WHEEL
pheval_ai_marrvel-0.2.0.dist-info/entry_points.txt
pheval_ai_marrvel-0.2.0.dist-info/RECORD
